pydantic_env/__init__.py
pydantic_env/models.py
pydantic_env-0.2.0.dist-info/LICENSE
pydantic_env-0.2.0.dist-info/METADATA
pydantic_env-0.2.0.dist-info/WHEEL
pydantic_env-0.2.0.dist-info/top_level.txt
pydantic_env-0.2.0.dist-info/RECORD
