Metadata-Version: 2.1
Name: pydantic-env
Version: 0.2.0
Summary: Pydantic Models for Environment
Home-page: UNKNOWN
Author: Jeremy Schulman
License: UNKNOWN
Platform: UNKNOWN
Classifier: Development Status :: 3 - Alpha
Classifier: Intended Audience :: Developers
Classifier: Programming Language :: Python :: 3.8
Classifier: Topic :: Software Development :: Libraries :: Python Modules
Classifier: Topic :: System :: Networking
Requires-Dist: first
Requires-Dist: pydantic
